scsu/__init__.py
scsu/__main__.py
scsu/codecs/decoder.py
scsu/codecs/encoder.py
scsu/codecs/info.py
scsu/codecs/states.py
scsu/codecs/tags.py
scsu/window/bases.py
scsu/window/bytes.py
scsu/window/candidates.py
scsu/window/supplement.py
scsu/window/types.py
scsu/window/unicode.py
scsu-1.1.1.dist-info/METADATA
scsu-1.1.1.dist-info/WHEEL
scsu-1.1.1.dist-info/licenses/LICENSE.txt
scsu-1.1.1.dist-info/RECORD
