Metadata-Version: 2.4
Name: scsu
Version: 1.1.1
Summary: Standard Compression Scheme for Unicode
Project-URL: Homepage, https://gitlab.com/gonard/scsu
Project-URL: Issues, https://gitlab.com/gonard/scsu/issues
Author-email: Gonard <gary@gonard.org>
License-Expression: MIT
License-File: LICENSE.txt
Classifier: Development Status :: 5 - Production/Stable
Classifier: Intended Audience :: Developers
Classifier: License :: OSI Approved :: MIT License
Classifier: Operating System :: OS Independent
Classifier: Programming Language :: Python :: 3
Classifier: Topic :: Software Development :: Libraries :: Python Modules
Classifier: Topic :: System :: Archiving :: Compression
Classifier: Topic :: Text Processing
Requires-Python: >=3.10
